[{"sentence": "Young voters less likely than older voters to say they were conta cted by political ", "bounding_box": [2, 14, 609, 31]}, {"sentence": "campaigns via printed mail, email for phone calls ", "bounding_box": [2, 34, 370, 52]}, {"sentence": "% who say before were contacted in the following ways by a candidate's campaign or a group supporting a candidate in the ", "bounding_box": [2, 58, 634, 75]}, {"sentence": "month before the election ", "bounding_box": [1, 74, 140, 89]}, {"sentence": "Printed mail ", "bounding_box": [96, 104, 161, 116]}, {"sentence": "Text ", "bounding_box": [236, 104, 261, 114]}, {"sentence": "Email ", "bounding_box": [336, 104, 368, 116]}, {"sentence": "Pre-recorded Phone call Home visit ", "bounding_box": [409, 102, 616, 117]}, {"sentence": "or flyers ", "bounding_box": [106, 118, 150, 132]}, {"sentence": "message ", "bounding_box": [224, 118, 273, 130]}, {"sentence": "phone call ", "bounding_box": [417, 120, 473, 132]}, {"sentence": "from live ", "bounding_box": [496, 120, 542, 130]}, {"sentence": "from ", "bounding_box": [574, 121, 600, 130]}, {"sentence": "person campaign rep ", "bounding_box": [501, 134, 624, 145]}, {"sentence": "or other group rep ", "bounding_box": [547, 145, 625, 160]}, {"sentence": "All voters ", "bounding_box": [28, 168, 74, 180]}, {"sentence": "78 ", "bounding_box": [126, 168, 141, 180]}, {"sentence": "64 ", "bounding_box": [244, 169, 258, 180]}, {"sentence": "60 ", "bounding_box": [346, 168, 362, 180]}, {"sentence": "48 ", "bounding_box": [440, 168, 456, 180]}, {"sentence": "32 ", "bounding_box": [517, 168, 534, 180]}, {"sentence": "White ", "bounding_box": [44, 217, 76, 228]}, {"sentence": "80 ", "bounding_box": [126, 217, 142, 229]}, {"sentence": "63 ", "bounding_box": [241, 217, 258, 229]}, {"sentence": "62 ", "bounding_box": [348, 217, 364, 229]}, {"sentence": "49 ", "bounding_box": [440, 217, 456, 229]}, {"sentence": "31 ", "bounding_box": [517, 217, 533, 229]}, {"sentence": "11 ", "bounding_box": [572, 217, 586, 229]}, {"sentence": "Black ", "bounding_box": [45, 241, 76, 253]}, {"sentence": "79 ", "bounding_box": [128, 244, 142, 254]}, {"sentence": "70 ", "bounding_box": [246, 242, 262, 254]}, {"sentence": "60 ", "bounding_box": [346, 242, 362, 254]}, {"sentence": "48 ", "bounding_box": [440, 242, 456, 254]}, {"sentence": "37 ", "bounding_box": [521, 242, 536, 254]}, {"sentence": "Hispanic ", "bounding_box": [29, 266, 76, 278]}, {"sentence": "72 ", "bounding_box": [122, 268, 137, 280]}, {"sentence": "67 ", "bounding_box": [245, 269, 260, 278]}, {"sentence": "57 ", "bounding_box": [345, 268, 360, 278]}, {"sentence": "38 ", "bounding_box": [433, 268, 449, 278]}, {"sentence": "30 ", "bounding_box": [517, 268, 533, 280]}, {"sentence": "Asian* ", "bounding_box": [38, 292, 74, 304]}, {"sentence": "55 ", "bounding_box": [344, 292, 360, 304]}, {"sentence": "38 ", "bounding_box": [433, 292, 449, 304]}, {"sentence": "25 ", "bounding_box": [513, 292, 529, 304]}, {"sentence": "62 ", "bounding_box": [116, 293, 130, 304]}, {"sentence": "59 ", "bounding_box": [240, 293, 256, 304]}, {"sentence": "Ages 18-29 ", "bounding_box": [14, 341, 74, 354]}, {"sentence": "29 ", "bounding_box": [428, 341, 444, 353]}, {"sentence": "24 ", "bounding_box": [513, 341, 529, 353]}, {"sentence": "55 ", "bounding_box": [110, 342, 128, 353]}, {"sentence": "62 ", "bounding_box": [241, 342, 257, 353]}, {"sentence": "50 ", "bounding_box": [341, 342, 357, 354]}, {"sentence": "30-49 ", "bounding_box": [42, 365, 76, 378]}, {"sentence": "74 ", "bounding_box": [124, 366, 138, 378]}, {"sentence": "69 ", "bounding_box": [245, 366, 261, 378]}, {"sentence": "57 ", "bounding_box": [346, 368, 360, 378]}, {"sentence": "43 ", "bounding_box": [437, 366, 453, 378]}, {"sentence": "29 ", "bounding_box": [516, 366, 532, 378]}, {"sentence": "50-64 ", "bounding_box": [42, 390, 74, 402]}, {"sentence": "85 ", "bounding_box": [130, 392, 146, 404]}, {"sentence": "66 ", "bounding_box": [244, 392, 260, 404]}, {"sentence": "65 ", "bounding_box": [350, 392, 366, 404]}, {"sentence": "49 ", "bounding_box": [440, 392, 457, 404]}, {"sentence": "31 ", "bounding_box": [517, 392, 533, 404]}, {"sentence": "65+ ", "bounding_box": [52, 416, 74, 428]}, {"sentence": "57 ", "bounding_box": [238, 416, 253, 428]}, {"sentence": "60 ", "bounding_box": [448, 416, 464, 428]}, {"sentence": "39 ", "bounding_box": [522, 416, 538, 428]}, {"sentence": "88 ", "bounding_box": [132, 417, 148, 428]}, {"sentence": "65 ", "bounding_box": [350, 417, 365, 428]}, {"sentence": "*Asians interviewed in English only, ", "bounding_box": [2, 448, 164, 460]}, {"sentence": "Notes: Based on voters. White, Black, and Asian adults include those who report being only one race and are not Hispanic Hispanics are of ", "bounding_box": [1, 461, 629, 474]}, {"sentence": "any race Survey No answer responses not shown. ", "bounding_box": [2, 477, 196, 488]}, {"sentence": "Source: Survey of U.S. adults conducted Nov, 12-17, 2020. ", "bounding_box": [1, 488, 269, 501]}, {"sentence": "PEW RESEARCH CENTER ", "bounding_box": [1, 506, 118, 518]}]