[{"sentence": "Fewer Republicans say local news ", "bounding_box": [1, 41, 525, 79]}, {"sentence": "media are connected to community ", "bounding_box": [2, 84, 544, 120]}, {"sentence": "% ofus adults who say local journalists/news media ", "bounding_box": [0, 137, 590, 164]}, {"sentence": "Are in touch with Rep/lean Rep ", "bounding_box": [24, 204, 357, 228]}, {"sentence": "61% ", "bounding_box": [425, 204, 473, 224]}, {"sentence": "the community Dem/lean Dem ", "bounding_box": [39, 232, 372, 263]}, {"sentence": "67% ", "bounding_box": [453, 238, 501, 260]}, {"sentence": "Mostly cover ", "bounding_box": [66, 296, 196, 321]}, {"sentence": "49 ", "bounding_box": [388, 308, 419, 331]}, {"sentence": "the area where ", "bounding_box": [37, 325, 194, 345]}, {"sentence": "54 ", "bounding_box": [412, 345, 441, 365]}, {"sentence": "you live ", "bounding_box": [113, 351, 195, 377]}, {"sentence": "Have a lot of ", "bounding_box": [66, 416, 196, 437]}, {"sentence": "34 ", "bounding_box": [320, 416, 350, 436]}, {"sentence": "influence ", "bounding_box": [97, 442, 195, 467]}, {"sentence": "40 ", "bounding_box": [347, 449, 378, 472]}, {"sentence": "Source: Survey conducted Oct. 15-Nov. 8, 2018. ", "bounding_box": [0, 528, 436, 550]}, {"sentence": "PEW RESEARCH CENTER ", "bounding_box": [0, 568, 232, 588]}]