[{"sentence": "Women are now significantly more likely ", "bounding_box": [0, 22, 309, 40]}, {"sentence": "to be college-educated than men ", "bounding_box": [0, 44, 250, 61]}, {"sentence": "% of25- to 64-year- olds completing a bachelor's degree ", "bounding_box": [0, 68, 302, 82]}, {"sentence": "or more ", "bounding_box": [1, 86, 46, 97]}, {"sentence": "38 ", "bounding_box": [280, 121, 297, 133]}, {"sentence": "33 ", "bounding_box": [280, 142, 297, 154]}, {"sentence": "Men ", "bounding_box": [128, 156, 156, 168]}, {"sentence": "Women ", "bounding_box": [166, 184, 216, 197]}, {"sentence": "23 ", "bounding_box": [14, 194, 32, 208]}, {"sentence": "15 ", "bounding_box": [14, 233, 32, 246]}, {"sentence": "1980 ", "bounding_box": [21, 325, 50, 337]}, {"sentence": "1990 ", "bounding_box": [90, 325, 121, 337]}, {"sentence": "2000 ", "bounding_box": [153, 325, 184, 337]}, {"sentence": "2010 2017 ", "bounding_box": [217, 325, 288, 337]}, {"sentence": "Note: For 1980- -1991 ofcollege figures shown are ofdegree the share who completed ", "bounding_box": [0, 354, 304, 368]}, {"sentence": "at leastfouryears ofcollege regardless ofdegree attainment. ", "bounding_box": [0, 368, 282, 381]}, {"sentence": "Source leastfouryears Pew Research Centeranalysis regardless of ofdegree 1980-2017 Current ", "bounding_box": [0, 381, 280, 393]}, {"sentence": "Population Survev Annua Social and Economic Supplement ", "bounding_box": [0, 394, 274, 407]}, {"sentence": "(IPUMS). ", "bounding_box": [0, 408, 41, 421]}, {"sentence": "PEW RESEARCH CENTER ", "bounding_box": [0, 428, 117, 438]}]