[{"sentence": "Younger Americans and men are among the most ", "bounding_box": [2, 21, 377, 38]}, {"sentence": "likely to play video games ", "bounding_box": [1, 42, 197, 60]}, {"sentence": "% ofadults saying they portable often, 'sometimes play video games on a computer, ", "bounding_box": [2, 66, 402, 82]}, {"sentence": "TV, game console, saying or portable device like a cellphone ", "bounding_box": [1, 82, 286, 97]}, {"sentence": "Sometimes ", "bounding_box": [237, 120, 298, 132]}, {"sentence": "Often ", "bounding_box": [160, 121, 190, 132]}, {"sentence": "Net ", "bounding_box": [372, 122, 393, 134]}, {"sentence": "Men ", "bounding_box": [96, 153, 120, 164]}, {"sentence": "24 ", "bounding_box": [194, 152, 210, 164]}, {"sentence": "23 ", "bounding_box": [280, 152, 296, 164]}, {"sentence": "47 ", "bounding_box": [376, 154, 389, 164]}, {"sentence": "21 ", "bounding_box": [254, 182, 269, 193]}, {"sentence": "Women ", "bounding_box": [78, 182, 120, 193]}, {"sentence": "19 ", "bounding_box": [177, 182, 193, 193]}, {"sentence": "39 ", "bounding_box": [373, 182, 389, 194]}, {"sentence": "White ", "bounding_box": [88, 212, 120, 224]}, {"sentence": "21 ", "bounding_box": [184, 212, 198, 224]}, {"sentence": "20 ", "bounding_box": [257, 212, 273, 224]}, {"sentence": "41 ", "bounding_box": [374, 214, 389, 225]}, {"sentence": "44 ", "bounding_box": [374, 244, 389, 257]}, {"sentence": "20 ", "bounding_box": [269, 241, 285, 253]}, {"sentence": "Black ", "bounding_box": [90, 242, 120, 253]}, {"sentence": "24 ", "bounding_box": [194, 242, 210, 253]}, {"sentence": "Hispanic ", "bounding_box": [73, 272, 120, 285]}, {"sentence": "18 ", "bounding_box": [173, 273, 189, 284]}, {"sentence": "29 ", "bounding_box": [280, 273, 296, 284]}, {"sentence": "48 ", "bounding_box": [373, 276, 389, 286]}, {"sentence": "Ages 18-29 ", "bounding_box": [59, 300, 120, 315]}, {"sentence": "29 ", "bounding_box": [214, 302, 229, 314]}, {"sentence": "31 ", "bounding_box": [329, 302, 344, 314]}, {"sentence": "60 ", "bounding_box": [374, 305, 389, 316]}, {"sentence": "30-49 ", "bounding_box": [86, 332, 120, 344]}, {"sentence": "28 ", "bounding_box": [210, 333, 226, 344]}, {"sentence": "25 ", "bounding_box": [302, 333, 318, 345]}, {"sentence": "53 ", "bounding_box": [374, 334, 389, 345]}, {"sentence": "50-64 ", "bounding_box": [86, 361, 120, 373]}, {"sentence": "15 ", "bounding_box": [162, 362, 177, 374]}, {"sentence": "17 ", "bounding_box": [225, 362, 240, 374]}, {"sentence": "31 ", "bounding_box": [373, 364, 389, 376]}, {"sentence": "65+ ", "bounding_box": [98, 394, 120, 404]}, {"sentence": "11 ", "bounding_box": [148, 393, 162, 405]}, {"sentence": "13 ", "bounding_box": [194, 393, 210, 404]}, {"sentence": "24 ", "bounding_box": [373, 394, 389, 406]}, {"sentence": "High school or less ", "bounding_box": [22, 422, 120, 437]}, {"sentence": "21 ", "bounding_box": [184, 422, 200, 434]}, {"sentence": "21 ", "bounding_box": [261, 422, 277, 434]}, {"sentence": "42 ", "bounding_box": [374, 425, 389, 437]}, {"sentence": "Some college ", "bounding_box": [49, 453, 120, 466]}, {"sentence": "25 ", "bounding_box": [198, 453, 214, 464]}, {"sentence": "25 ", "bounding_box": [292, 453, 308, 464]}, {"sentence": "50 ", "bounding_box": [374, 454, 389, 466]}, {"sentence": "Bach elor's degree+ ", "bounding_box": [19, 482, 120, 496]}, {"sentence": "17 ", "bounding_box": [169, 482, 184, 494]}, {"sentence": "19 ", "bounding_box": [240, 482, 256, 494]}, {"sentence": "36 ", "bounding_box": [373, 486, 390, 497]}, {"sentence": "Note: Figures may notadd to subtotals due to rounding White and blacks include only ", "bounding_box": [2, 525, 393, 538]}, {"sentence": "non-Hispa nics. Hispanics are ofany race. ", "bounding_box": [1, 538, 190, 550]}, {"sentence": "non-Hispa Source: Survey ofU.S. adults ofany conducted March 13-27 and April4-18 2017 ", "bounding_box": [1, 550, 343, 564]}, {"sentence": "PEW RESEARCH CENTER ", "bounding_box": [2, 570, 120, 581]}]