[{"sentence": "Americans are divided about media ", "bounding_box": [1, 13, 268, 29]}, {"sentence": "coverage of protests these days ", "bounding_box": [0, 33, 242, 52]}, {"sentence": "% of U.S. adults who say news organizations give ", "bounding_box": [0, 59, 269, 74]}, {"sentence": "the coverage to protests, say marches organizations and demonstrations give these ", "bounding_box": [0, 73, 305, 91]}, {"sentence": "the compared with recent years ", "bounding_box": [0, 90, 184, 108]}, {"sentence": "Too much ", "bounding_box": [28, 121, 77, 132]}, {"sentence": "About the rightamount Too little ", "bounding_box": [101, 120, 289, 133]}, {"sentence": "US ad ults ", "bounding_box": [28, 146, 85, 158]}, {"sentence": "41 ", "bounding_box": [157, 149, 172, 158]}, {"sentence": "31 ", "bounding_box": [224, 149, 238, 160]}, {"sentence": "24 ", "bounding_box": [264, 148, 280, 160]}, {"sentence": "Rep/Lean Rep ", "bounding_box": [10, 201, 85, 214]}, {"sentence": "68 ", "bounding_box": [216, 202, 230, 212]}, {"sentence": "18 11 ", "bounding_box": [254, 202, 296, 213]}, {"sentence": "Dem/Lean Dem ", "bounding_box": [2, 228, 85, 240]}, {"sentence": "26 ", "bounding_box": [122, 228, 138, 240]}, {"sentence": "43 ", "bounding_box": [216, 228, 233, 240]}, {"sentence": "29 ", "bounding_box": [264, 228, 278, 240]}, {"sentence": "Note: Respondents who did not give 2017 ananswerare notshown. ", "bounding_box": [0, 265, 284, 278]}, {"sentence": "Source Survey conducted May3-7, give 2017 ", "bounding_box": [0, 277, 189, 291]}, {"sentence": "\"Americans Divided on Whether Recent Science Protests Will ", "bounding_box": [0, 292, 278, 304]}, {"sentence": "Benefit Scientists' Ca uses ", "bounding_box": [0, 305, 122, 317]}, {"sentence": "PEW RESEARCH CENTER ", "bounding_box": [0, 324, 118, 334]}]