[{"sentence": "Views of Putin, Netanyahu and Merkel ", "bounding_box": [0, 13, 289, 30]}, {"sentence": "% who have a ", "bounding_box": [0, 37, 76, 50]}, {"sentence": "of ", "bounding_box": [101, 38, 124, 52]}, {"sentence": "Favorable Unfa wora bole No opinion ", "bounding_box": [93, 61, 301, 76]}, {"sentence": "Putin ", "bounding_box": [42, 88, 72, 98]}, {"sentence": "19 ", "bounding_box": [94, 89, 109, 100]}, {"sentence": "13 ", "bounding_box": [280, 89, 296, 101]}, {"sentence": "Netanyahu ", "bounding_box": [14, 124, 72, 136]}, {"sentence": "34 ", "bounding_box": [109, 125, 125, 136]}, {"sentence": "32 ", "bounding_box": [182, 125, 198, 136]}, {"sentence": "33 ", "bounding_box": [253, 125, 269, 136]}, {"sentence": "29 ", "bounding_box": [105, 160, 120, 172]}, {"sentence": "23 ", "bounding_box": [161, 160, 177, 172]}, {"sentence": "Merkel ", "bounding_box": [36, 161, 72, 172]}, {"sentence": "48 ", "bounding_box": [241, 162, 256, 172]}, {"sentence": "Note Figures may notadd to 100% because ofrounding Q51 ", "bounding_box": [0, 194, 282, 208]}, {"sentence": "Source: Figures Survey conducted Jan 499, 2017. ", "bounding_box": [0, 208, 190, 220]}, {"sentence": "PEW RESEARCH CENTER ", "bounding_box": [0, 226, 117, 238]}]