[{"sentence": "Democrats and Republicans in U.S. differ on UN favorability ", "bounding_box": [2, 14, 455, 33]}, {"sentence": "% among who say they have afavorable view of the United Nations ", "bounding_box": [1, 40, 394, 54]}, {"sentence": "100 % ", "bounding_box": [5, 64, 40, 76]}, {"sentence": "85 ", "bounding_box": [216, 85, 232, 96]}, {"sentence": "85 ", "bounding_box": [544, 84, 560, 96]}, {"sentence": "79 81 ", "bounding_box": [77, 90, 115, 113]}, {"sentence": "80 81 ", "bounding_box": [466, 92, 502, 110]}, {"sentence": "Democrats ", "bounding_box": [561, 96, 621, 108]}, {"sentence": "72 79 78 ", "bounding_box": [162, 96, 200, 115]}, {"sentence": "77 ", "bounding_box": [511, 103, 544, 117]}, {"sentence": "75 ", "bounding_box": [285, 110, 298, 120]}, {"sentence": "68 74 72 79 ", "bounding_box": [128, 107, 166, 130]}, {"sentence": "72 ", "bounding_box": [349, 114, 366, 128]}, {"sentence": "7170 72 ", "bounding_box": [381, 113, 434, 134]}, {"sentence": "68 ", "bounding_box": [114, 125, 130, 136]}, {"sentence": "8 ", "bounding_box": [268, 128, 281, 136]}, {"sentence": "668 69 ", "bounding_box": [16, 140, 29, 149]}, {"sentence": "59 ", "bounding_box": [321, 144, 334, 152]}, {"sentence": "668 ", "bounding_box": [16, 149, 29, 158]}, {"sentence": "Independents ", "bounding_box": [558, 152, 633, 164]}, {"sentence": "68 ", "bounding_box": [181, 157, 197, 169]}, {"sentence": "67 ", "bounding_box": [216, 161, 229, 170]}, {"sentence": "a 62 ", "bounding_box": [152, 173, 181, 184]}, {"sentence": "48 ", "bounding_box": [536, 174, 552, 185]}, {"sentence": "58 56 56 a 62 ", "bounding_box": [111, 180, 165, 201]}, {"sentence": "51 ", "bounding_box": [384, 198, 400, 210]}, {"sentence": "48 ", "bounding_box": [401, 206, 417, 217]}, {"sentence": "Republicans ", "bounding_box": [564, 213, 632, 225]}, {"sentence": "45 4142 ", "bounding_box": [265, 213, 282, 224]}, {"sentence": "43 44 ", "bounding_box": [465, 213, 502, 231]}, {"sentence": "45 4142 38 ", "bounding_box": [281, 217, 317, 236]}, {"sentence": "41 ", "bounding_box": [417, 222, 433, 234]}, {"sentence": "39 ", "bounding_box": [542, 226, 560, 238]}, {"sentence": "38 ", "bounding_box": [317, 230, 332, 241]}, {"sentence": "36 ", "bounding_box": [518, 234, 534, 246]}, {"sentence": "1990 ", "bounding_box": [22, 320, 53, 332]}, {"sentence": "1993 ", "bounding_box": [73, 320, 104, 332]}, {"sentence": "1996 ", "bounding_box": [124, 320, 154, 332]}, {"sentence": "1999 ", "bounding_box": [174, 320, 205, 332]}, {"sentence": "2002 ", "bounding_box": [225, 320, 256, 332]}, {"sentence": "2005 ", "bounding_box": [276, 320, 306, 332]}, {"sentence": "2008 ", "bounding_box": [326, 320, 356, 332]}, {"sentence": "2011 ", "bounding_box": [377, 320, 406, 332]}, {"sentence": "2014 ", "bounding_box": [426, 320, 457, 332]}, {"sentence": "2017 ", "bounding_box": [478, 321, 508, 332]}, {"sentence": "2020 ", "bounding_box": [528, 320, 558, 332]}, {"sentence": "Note: Beca use some earlier data did not include partisan leaning Republicans and Democrats in this graphic do not include leaners ", "bounding_box": [0, 340, 597, 352]}, {"sentence": "Source: Pew Research Center surveys 1990 2003, 2005 and 2017 Summer 2020 Global Attitudes Survey. q8e ", "bounding_box": [0, 353, 509, 365]}, {"sentence": "\"International Cooperation We comed Across 14 Advanced Economies ", "bounding_box": [1, 366, 322, 378]}, {"sentence": "PEW RESEARCH CENTER ", "bounding_box": [0, 385, 117, 397]}]