[{"sentence": "Canadians Favor Strong ", "bounding_box": [0, 11, 182, 30]}, {"sentence": "Economic Ties with U.S. ", "bounding_box": [1, 34, 178, 49]}, {"sentence": "Is itmore important for Canada to ", "bounding_box": [0, 58, 189, 73]}, {"sentence": "have strong economic ties with China ", "bounding_box": [0, 74, 202, 89]}, {"sentence": "or the U.S.? ", "bounding_box": [0, 90, 64, 104]}, {"sentence": "73% ", "bounding_box": [52, 185, 77, 197]}, {"sentence": "U.S. ", "bounding_box": [114, 185, 136, 197]}, {"sentence": "13 ", "bounding_box": [57, 274, 73, 286]}, {"sentence": "China ", "bounding_box": [114, 274, 148, 286]}, {"sentence": "Neithers both ", "bounding_box": [114, 290, 172, 314]}, {"sentence": "10 ", "bounding_box": [57, 297, 73, 309]}, {"sentence": "Don't know ", "bounding_box": [114, 314, 173, 326]}, {"sentence": "Source: Spring 2015 Global Attitudes ", "bounding_box": [0, 344, 172, 357]}, {"sentence": "survey. Q26v. ", "bounding_box": [1, 358, 65, 369]}, {"sentence": "PEW RESEARCH CENTER ", "bounding_box": [0, 376, 118, 388]}]