[{"sentence": "Wide partisan differences in views about social media ", "bounding_box": [6, 31, 820, 64]}, {"sentence": "companies labeling posts from elected officials as ", "bounding_box": [5, 70, 765, 103]}, {"sentence": "misleading or inaccurate ", "bounding_box": [6, 110, 382, 145]}, {"sentence": "% of U.S. adults who say they of social media companies ", "bounding_box": [8, 169, 744, 200]}, {"sentence": "labeling posts on their platforms from elected officials companies as ", "bounding_box": [8, 203, 708, 236]}, {"sentence": "inaccurate or misleading ", "bounding_box": [6, 236, 318, 270]}, {"sentence": "Disapprove ", "bounding_box": [375, 295, 485, 318]}, {"sentence": "Approve ", "bounding_box": [531, 296, 611, 316]}, {"sentence": "U.S. adults ", "bounding_box": [12, 341, 119, 361]}, {"sentence": "46 ", "bounding_box": [330, 341, 360, 361]}, {"sentence": "51 ", "bounding_box": [675, 341, 702, 361]}, {"sentence": "Rep/Lean Rep ", "bounding_box": [11, 391, 157, 417]}, {"sentence": "71 ", "bounding_box": [230, 391, 256, 410]}, {"sentence": "27 ", "bounding_box": [578, 391, 605, 412]}, {"sentence": "Dem/Lean Dem ", "bounding_box": [12, 443, 171, 465]}, {"sentence": "25 ", "bounding_box": [418, 443, 446, 463]}, {"sentence": "73 ", "bounding_box": [765, 443, 792, 463]}, {"sentence": "% of U.S. adults who say they have ", "bounding_box": [8, 538, 439, 567]}, {"sentence": "(of confidence in social ", "bounding_box": [484, 538, 779, 566]}, {"sentence": "media companies to determine which posts on their platforms ", "bounding_box": [8, 573, 770, 604]}, {"sentence": "should companies be labeled as innaccurate or misleading ", "bounding_box": [8, 604, 587, 638]}, {"sentence": "a fair ", "bounding_box": [536, 685, 590, 706]}, {"sentence": "None ", "bounding_box": [269, 686, 322, 706]}, {"sentence": "Not too ", "bounding_box": [394, 687, 467, 704]}, {"sentence": "A great ", "bounding_box": [618, 687, 690, 708]}, {"sentence": "at all ", "bounding_box": [268, 713, 320, 730]}, {"sentence": "much ", "bounding_box": [403, 713, 458, 730]}, {"sentence": "amount deal ", "bounding_box": [524, 713, 661, 730]}, {"sentence": "U. S adults ", "bounding_box": [12, 763, 119, 782]}, {"sentence": "29 ", "bounding_box": [280, 763, 309, 782]}, {"sentence": "38 ", "bounding_box": [417, 763, 444, 782]}, {"sentence": "27 ", "bounding_box": [548, 763, 574, 782]}, {"sentence": "Rep/Lean Rep ", "bounding_box": [12, 813, 157, 837]}, {"sentence": "50 ", "bounding_box": [254, 813, 283, 832]}, {"sentence": "34 ", "bounding_box": [425, 813, 451, 832]}, {"sentence": "12 2 ", "bounding_box": [521, 813, 583, 832]}, {"sentence": "40 ", "bounding_box": [574, 862, 602, 882]}, {"sentence": "Dem/ Lean Dem ", "bounding_box": [12, 863, 169, 884]}, {"sentence": "11 ", "bounding_box": [306, 863, 334, 882]}, {"sentence": "41 ", "bounding_box": [408, 863, 436, 882]}, {"sentence": "Note: Strongly/somewhat approve or disapprove responses ware combined. Those who did ", "bounding_box": [5, 931, 805, 953]}, {"sentence": "not give an answer are not shown ", "bounding_box": [5, 959, 308, 979]}, {"sentence": "Source: Survey of U.S adults conducted June 16-22 2020 ", "bounding_box": [3, 985, 533, 1005]}, {"sentence": "Most Americans Think Social Media Sites Censor Political Viewpoints\" ", "bounding_box": [5, 1011, 635, 1033]}, {"sentence": "PEW RESEARCH CENTER ", "bounding_box": [5, 1050, 231, 1069]}]