[{"sentence": "Dysfunctional Government Most Important Problem Facing America Today ", "bounding_box": [22, 12, 497, 29]}, {"sentence": "Monthly trend, January 2008 October 2013 ", "bounding_box": [21, 36, 265, 50]}, {"sentence": "Economy in general ", "bounding_box": [41, 61, 152, 77]}, {"sentence": "Unemployment/Johs ", "bounding_box": [276, 61, 397, 76]}, {"sentence": "Government/Ongress) Politicians ", "bounding_box": [41, 89, 232, 104]}, {"sentence": "58 ", "bounding_box": [112, 126, 126, 138]}, {"sentence": "60 ", "bounding_box": [22, 132, 38, 144]}, {"sentence": "50 ", "bounding_box": [22, 161, 38, 174]}, {"sentence": "40 ", "bounding_box": [24, 190, 38, 201]}, {"sentence": "30 ", "bounding_box": [22, 217, 38, 230]}, {"sentence": "20 ", "bounding_box": [24, 246, 38, 257]}, {"sentence": "10 ", "bounding_box": [25, 274, 38, 284]}, {"sentence": "a ", "bounding_box": [32, 304, 38, 312]}, {"sentence": "2009 ", "bounding_box": [114, 321, 146, 333]}, {"sentence": "2010 ", "bounding_box": [201, 321, 230, 332]}, {"sentence": "2011 ", "bounding_box": [289, 321, 316, 332]}, {"sentence": "2012 ", "bounding_box": [374, 321, 404, 332]}, {"sentence": "2013 ", "bounding_box": [461, 321, 490, 333]}, {"sentence": "GALLUP ", "bounding_box": [20, 351, 75, 365]}]