[{"sentence": "Americans Conflicted ", "bounding_box": [1, 7, 178, 23]}, {"sentence": "fover Internationalism ", "bounding_box": [0, 24, 182, 40]}, {"sentence": "The U.S should take into account ", "bounding_box": [0, 50, 184, 64]}, {"sentence": "the views of its major allies. ", "bounding_box": [0, 64, 154, 76]}, {"sentence": "81 ", "bounding_box": [6, 100, 21, 112]}, {"sentence": "78 ", "bounding_box": [161, 106, 176, 116]}, {"sentence": "Agree ", "bounding_box": [64, 142, 100, 156]}, {"sentence": "Disagree ", "bounding_box": [56, 211, 109, 228]}, {"sentence": "64 69 74 79 84 89 94 99 00 09 ", "bounding_box": [6, 262, 176, 274]}, {"sentence": "The interna ULS should tiona go tters its own way ", "bounding_box": [0, 277, 174, 293]}, {"sentence": "in interna tiona ma go tters not way ", "bounding_box": [0, 290, 157, 302]}, {"sentence": "in worrying interna tiona too much ma with tters whether not other ", "bounding_box": [0, 301, 182, 316]}, {"sentence": "worrying countries too agree much with whether us or not. other ", "bounding_box": [0, 313, 169, 328]}, {"sentence": "Disagree ", "bounding_box": [63, 350, 117, 365]}, {"sentence": "70 ", "bounding_box": [10, 381, 24, 390]}, {"sentence": "19 ", "bounding_box": [9, 446, 25, 458]}, {"sentence": "Agree ", "bounding_box": [68, 466, 104, 480]}, {"sentence": "64 6974 79 84 89 9499 04 09 ", "bounding_box": [9, 512, 168, 524]}, {"sentence": "We int'l should not think so much in ", "bounding_box": [0, 534, 173, 548]}, {"sentence": "int'l terms but concentrate problems. more ", "bounding_box": [1, 548, 180, 560]}, {"sentence": "int'l on our terms own but nationa concentrate problems. more ", "bounding_box": [0, 558, 168, 572]}, {"sentence": "Agree ", "bounding_box": [58, 602, 94, 616]}, {"sentence": "76 ", "bounding_box": [161, 606, 176, 616]}, {"sentence": "55 ", "bounding_box": [6, 638, 21, 650]}, {"sentence": "32 ", "bounding_box": [6, 677, 21, 688]}, {"sentence": "19 ", "bounding_box": [152, 716, 168, 728]}, {"sentence": "Disagree ", "bounding_box": [51, 728, 105, 743]}, {"sentence": "64 69 74 79 84 89 94 99 00 09 ", "bounding_box": [6, 758, 176, 770]}, {"sentence": "PEW RESEARCH CENTER Nov 2009 ", "bounding_box": [0, 778, 165, 790]}]