[{"sentence": "Public's Better, View of Job Situation: ", "bounding_box": [1, 9, 253, 25]}, {"sentence": "Public's Better, Still View Not of Good Job Situation: ", "bounding_box": [2, 23, 176, 43]}, {"sentence": "Availability ofjobs in your community ", "bounding_box": [1, 50, 209, 67]}, {"sentence": "85 ", "bounding_box": [197, 90, 213, 102]}, {"sentence": "Jobs are difficult to find ", "bounding_box": [40, 104, 172, 117]}, {"sentence": "78 ", "bounding_box": [240, 105, 256, 116]}, {"sentence": "66 ", "bounding_box": [62, 130, 78, 141]}, {"sentence": "61 ", "bounding_box": [160, 137, 172, 146]}, {"sentence": "60 ", "bounding_box": [98, 142, 112, 152]}, {"sentence": "42 ", "bounding_box": [16, 209, 29, 217]}, {"sentence": "29 ", "bounding_box": [272, 208, 285, 217]}, {"sentence": "30 ", "bounding_box": [98, 228, 112, 238]}, {"sentence": "16 ", "bounding_box": [236, 228, 253, 240]}, {"sentence": "30 ", "bounding_box": [158, 230, 173, 242]}, {"sentence": "24 ", "bounding_box": [62, 237, 78, 249]}, {"sentence": "Plenty of jobs are available ", "bounding_box": [25, 256, 176, 269]}, {"sentence": "10 ", "bounding_box": [197, 266, 213, 278]}, {"sentence": "01 02 03 04 05 06 07 08 09 10 11 12 13 ", "bounding_box": [5, 290, 273, 302]}, {"sentence": "PEW RESEARCH CENTER June 12-16, 2013, Q32, ", "bounding_box": [1, 313, 233, 325]}]