[{"sentence": "Teens Online Shopping ", "bounding_box": [0, 18, 182, 38]}, {"sentence": "Do you shop online? ", "bounding_box": [0, 52, 128, 68]}, {"sentence": "NO ", "bounding_box": [141, 72, 157, 82]}, {"sentence": "YES ", "bounding_box": [228, 72, 249, 84]}, {"sentence": "Female ", "bounding_box": [10, 94, 57, 108]}, {"sentence": "20% ", "bounding_box": [165, 97, 189, 109]}, {"sentence": "79% ", "bounding_box": [268, 97, 294, 110]}, {"sentence": "Male ", "bounding_box": [12, 126, 42, 140]}, {"sentence": "24 ", "bounding_box": [160, 126, 177, 138]}, {"sentence": "76 ", "bounding_box": [272, 126, 289, 138]}, {"sentence": "Do you prefer to shop online or in stores? ", "bounding_box": [0, 164, 260, 180]}, {"sentence": "IN STORES ", "bounding_box": [105, 189, 160, 201]}, {"sentence": "ONLINE ", "bounding_box": [228, 189, 268, 201]}, {"sentence": "Female ", "bounding_box": [10, 210, 57, 224]}, {"sentence": "78% ", "bounding_box": [78, 212, 102, 224]}, {"sentence": "17% ", "bounding_box": [192, 212, 216, 224]}, {"sentence": "Male ", "bounding_box": [10, 246, 42, 260]}, {"sentence": "19 ", "bounding_box": [198, 246, 216, 260]}, {"sentence": "75 ", "bounding_box": [82, 248, 98, 260]}, {"sentence": "Source: Piper Jaffray & Co. POP Quiz ", "bounding_box": [0, 280, 185, 293]}, {"sentence": "PEW RESEARCH CENTER ", "bounding_box": [0, 301, 132, 314]}]