[{"sentence": "Youth Since 2008 Engagement Down Sharply ", "bounding_box": [2, 10, 281, 28]}, {"sentence": "Since 2008 Engagement ", "bounding_box": [2, 26, 95, 41]}, {"sentence": "% of voters who are highly engaged in the election ", "bounding_box": [2, 52, 281, 66]}, {"sentence": "Sept 2008 I Sept 2012 ", "bounding_box": [86, 77, 230, 90]}, {"sentence": "91 ", "bounding_box": [198, 102, 212, 112]}, {"sentence": "87 ", "bounding_box": [153, 109, 166, 120]}, {"sentence": "86 ", "bounding_box": [20, 110, 33, 120]}, {"sentence": "85 86 86 ", "bounding_box": [215, 107, 277, 123]}, {"sentence": "80 ", "bounding_box": [38, 120, 52, 130]}, {"sentence": "77 ", "bounding_box": [172, 121, 186, 130]}, {"sentence": "75 ", "bounding_box": [108, 126, 124, 138]}, {"sentence": "18-29 30-49 50-64 ", "bounding_box": [109, 273, 232, 285]}, {"sentence": "All ", "bounding_box": [28, 274, 42, 284]}, {"sentence": "65+ ", "bounding_box": [246, 273, 270, 284]}, {"sentence": "voters ", "bounding_box": [17, 288, 54, 297]}, {"sentence": "PEW RESEARCH CENTER, Sept. 12-16, 2012, Based on ", "bounding_box": [2, 305, 262, 317]}, {"sentence": "registered PEW udes RESEARCH four voters measures CENTER, Engage ofinterestin Sept. mentis 12-16, based the 2012, on campaign a scale Based that and on ", "bounding_box": [1, 316, 265, 340]}, {"sentence": "intention to vote ", "bounding_box": [2, 340, 86, 349]}]