[{"sentence": "National Economic Ratings ", "bounding_box": [62, 9, 229, 25]}, {"sentence": "Personal Economic Ratings ", "bounding_box": [347, 9, 518, 25]}, {"sentence": "ExcellentiGood ", "bounding_box": [114, 29, 194, 42]}, {"sentence": "Excellentfood ", "bounding_box": [398, 32, 480, 45]}, {"sentence": "OnlyfairPPoor ", "bounding_box": [113, 50, 188, 64]}, {"sentence": "OnlyfairiPoor ", "bounding_box": [398, 53, 473, 66]}, {"sentence": "95 ", "bounding_box": [229, 54, 245, 68]}, {"sentence": "88 ", "bounding_box": [190, 74, 205, 86]}, {"sentence": ".391 ", "bounding_box": [261, 77, 281, 86]}, {"sentence": "66 ", "bounding_box": [554, 134, 570, 146]}, {"sentence": "55 ", "bounding_box": [361, 149, 374, 160]}, {"sentence": "610 ", "bounding_box": [141, 157, 154, 166]}, {"sentence": "60 ", "bounding_box": [60, 157, 74, 169]}, {"sentence": "48 ", "bounding_box": [321, 177, 340, 186]}, {"sentence": "39 ", "bounding_box": [61, 181, 76, 193]}, {"sentence": "35 ", "bounding_box": [557, 204, 570, 214]}, {"sentence": "25 ", "bounding_box": [92, 234, 106, 246]}, {"sentence": "1104 ", "bounding_box": [12, 297, 36, 310]}, {"sentence": "100 ", "bounding_box": [53, 297, 77, 310]}, {"sentence": "1106 ", "bounding_box": [93, 297, 118, 310]}, {"sentence": "1107 ", "bounding_box": [136, 297, 161, 310]}, {"sentence": "1108 ", "bounding_box": [178, 297, 202, 310]}, {"sentence": "1109 ", "bounding_box": [218, 297, 244, 310]}, {"sentence": "1104 ", "bounding_box": [298, 297, 324, 310]}, {"sentence": "100 ", "bounding_box": [340, 297, 365, 310]}, {"sentence": "1106 ", "bounding_box": [381, 297, 405, 310]}, {"sentence": "1107 ", "bounding_box": [422, 297, 448, 310]}, {"sentence": "1108 ", "bounding_box": [465, 297, 489, 310]}, {"sentence": "1109 ", "bounding_box": [505, 297, 530, 310]}]