[{"sentence": "Intern ational New S Sto ries People Have -- and Have Not INTERTARIZED Heard Ab out ", "bounding_box": [57, 6, 573, 24]}, {"sentence": "Abu Ghraibi ", "bounding_box": [417, 36, 493, 48]}, {"sentence": "The bird flu ", "bounding_box": [78, 37, 149, 50]}, {"sentence": "Global ", "bounding_box": [208, 37, 250, 50]}, {"sentence": "Iran nuclear ", "bounding_box": [305, 37, 382, 49]}, {"sentence": "Hamas ", "bounding_box": [548, 37, 592, 49]}, {"sentence": "Guantanamo ", "bounding_box": [414, 52, 494, 65]}, {"sentence": "dispute ", "bounding_box": [321, 54, 366, 68]}, {"sentence": "election ", "bounding_box": [542, 54, 593, 66]}, {"sentence": "disease ", "bounding_box": [90, 56, 137, 68]}, {"sentence": "warming ", "bounding_box": [202, 56, 257, 69]}, {"sentence": "abuses ", "bounding_box": [432, 69, 477, 80]}, {"sentence": "58 ", "bounding_box": [520, 81, 536, 92]}, {"sentence": "US 92 ", "bounding_box": [34, 82, 85, 96]}, {"sentence": "83 ", "bounding_box": [296, 84, 310, 93]}, {"sentence": "91 ", "bounding_box": [184, 85, 194, 94]}, {"sentence": "85 ", "bounding_box": [521, 112, 536, 122]}, {"sentence": "9 ", "bounding_box": [296, 113, 308, 122]}, {"sentence": "9 8 ", "bounding_box": [409, 113, 422, 122]}, {"sentence": "Germ any I 00 ", "bounding_box": [10, 114, 92, 126]}, {"sentence": "95 ", "bounding_box": [182, 113, 196, 124]}, {"sentence": "83 ", "bounding_box": [520, 125, 536, 137]}, {"sentence": "France 00 ", "bounding_box": [21, 127, 92, 140]}, {"sentence": "97 ", "bounding_box": [182, 126, 194, 138]}, {"sentence": "8 ", "bounding_box": [294, 126, 310, 138]}, {"sentence": "38 ", "bounding_box": [409, 129, 422, 137]}, {"sentence": "61 ", "bounding_box": [521, 141, 533, 150]}, {"sentence": "8 ", "bounding_box": [296, 142, 309, 152]}, {"sentence": "Britain 97 ", "bounding_box": [24, 144, 84, 154]}, {"sentence": "100 ", "bounding_box": [184, 144, 204, 153]}, {"sentence": "68 ", "bounding_box": [520, 156, 536, 166]}, {"sentence": "Spain 99 ", "bounding_box": [26, 157, 85, 170]}, {"sentence": "93 ", "bounding_box": [181, 157, 197, 168]}, {"sentence": "9 Q ", "bounding_box": [408, 158, 422, 168]}, {"sentence": "52 ", "bounding_box": [520, 169, 534, 181]}, {"sentence": "58 ", "bounding_box": [408, 170, 422, 182]}, {"sentence": "Russia 98 ", "bounding_box": [18, 172, 85, 184]}, {"sentence": "80 ", "bounding_box": [182, 172, 196, 182]}, {"sentence": "Jordan 98 ", "bounding_box": [21, 202, 85, 214]}, {"sentence": "48 ", "bounding_box": [184, 202, 196, 212]}, {"sentence": "9 ", "bounding_box": [521, 202, 534, 212]}, {"sentence": "98 ", "bounding_box": [521, 216, 536, 226]}, {"sentence": "Turkey Egyypt 96 ", "bounding_box": [27, 215, 85, 231]}, {"sentence": "47 ", "bounding_box": [184, 217, 194, 226]}, {"sentence": "80 ", "bounding_box": [408, 217, 422, 226]}, {"sentence": "68 ", "bounding_box": [408, 229, 422, 241]}, {"sentence": "56 ", "bounding_box": [520, 229, 536, 241]}, {"sentence": "Turkey 97 ", "bounding_box": [24, 232, 84, 244]}, {"sentence": "75 ", "bounding_box": [182, 230, 196, 242]}, {"sentence": "35 ", "bounding_box": [182, 244, 196, 256]}, {"sentence": "31 ", "bounding_box": [521, 245, 533, 254]}, {"sentence": "Indones ", "bounding_box": [10, 245, 60, 257]}, {"sentence": "99 ", "bounding_box": [70, 245, 85, 256]}, {"sentence": "28 ", "bounding_box": [409, 246, 422, 256]}, {"sentence": "21 ", "bounding_box": [409, 261, 420, 270]}, {"sentence": "20 ", "bounding_box": [520, 260, 536, 272]}, {"sentence": "Pakistan 82 ", "bounding_box": [10, 261, 85, 273]}, {"sentence": "Nigeria 98 ", "bounding_box": [18, 289, 85, 302]}, {"sentence": "42 ", "bounding_box": [182, 292, 196, 301]}, {"sentence": "8 ", "bounding_box": [297, 320, 310, 329]}, {"sentence": "Japan 99 ", "bounding_box": [25, 321, 85, 332]}, {"sentence": "99 ", "bounding_box": [182, 320, 196, 330]}, {"sentence": "78 ", "bounding_box": [184, 334, 196, 345]}, {"sentence": "27 ", "bounding_box": [520, 333, 534, 345]}, {"sentence": "China 93 ", "bounding_box": [26, 336, 85, 346]}, {"sentence": "38 ", "bounding_box": [409, 336, 422, 345]}, {"sentence": "21 ", "bounding_box": [521, 348, 533, 358]}, {"sentence": "50 ", "bounding_box": [297, 349, 310, 358]}, {"sentence": "23 ", "bounding_box": [408, 348, 422, 358]}, {"sentence": "India 99 ", "bounding_box": [32, 350, 85, 360]}, {"sentence": "57 ", "bounding_box": [184, 350, 194, 360]}, {"sentence": "Percent who have heard of each news item ", "bounding_box": [6, 380, 213, 392]}]