[{"sentence": "Unauthorized Adults Are ", "bounding_box": [101, 0, 494, 30]}, {"sentence": "Much Less Educated than Others ", "bounding_box": [32, 34, 562, 64]}, {"sentence": "Share of Each Group 's 25-64 Population, 2004 ", "bounding_box": [347, 74, 591, 89]}, {"sentence": "Unauthorized Migrants ", "bounding_box": [95, 78, 226, 96]}, {"sentence": "32% ", "bounding_box": [5, 89, 41, 106]}, {"sentence": "32% ", "bounding_box": [314, 92, 346, 108]}, {"sentence": "32% ", "bounding_box": [517, 98, 550, 113]}, {"sentence": "Legal Immigrants ", "bounding_box": [94, 104, 196, 120]}, {"sentence": "30% ", "bounding_box": [552, 110, 585, 126]}, {"sentence": "29% ", "bounding_box": [431, 116, 464, 133]}, {"sentence": "Natives ", "bounding_box": [96, 126, 142, 140]}, {"sentence": "25% 25% ", "bounding_box": [241, 140, 315, 171]}, {"sentence": "18% ", "bounding_box": [400, 200, 432, 217]}, {"sentence": "17% ", "bounding_box": [124, 209, 160, 228]}, {"sentence": "15% ", "bounding_box": [481, 224, 517, 241]}, {"sentence": "15% ", "bounding_box": [42, 226, 74, 242]}, {"sentence": "10% ", "bounding_box": [361, 261, 397, 278]}, {"sentence": "10% ", "bounding_box": [162, 264, 193, 280]}, {"sentence": "7% ", "bounding_box": [200, 289, 222, 305]}, {"sentence": "2% ", "bounding_box": [79, 327, 105, 344]}, {"sentence": "Less than 9th ", "bounding_box": [16, 380, 98, 394]}, {"sentence": "9th- 12th Grade ", "bounding_box": [130, 380, 221, 394]}, {"sentence": "High School ", "bounding_box": [260, 380, 332, 396]}, {"sentence": "Some College ", "bounding_box": [373, 378, 456, 396]}, {"sentence": "Bachelor's Degree ", "bounding_box": [478, 378, 589, 396]}, {"sentence": "Grade ", "bounding_box": [38, 398, 77, 413]}, {"sentence": "Diploma ", "bounding_box": [270, 398, 320, 414]}, {"sentence": "or More Degree ", "bounding_box": [509, 397, 557, 413]}]