[{"sentence": "A smaller but still sizable majority says ", "bounding_box": [6, 30, 594, 68]}, {"sentence": "nation's partisan divide is increasing ", "bounding_box": [6, 75, 562, 107]}, {"sentence": "% who say they think divisions between Republicans and ", "bounding_box": [6, 124, 617, 150]}, {"sentence": "Democrats in this country today are ", "bounding_box": [6, 157, 420, 182]}, {"sentence": "Staying the same ", "bounding_box": [244, 210, 420, 233]}, {"sentence": "Decreasing ", "bounding_box": [466, 208, 583, 233]}, {"sentence": "Increasing ", "bounding_box": [92, 211, 200, 233]}, {"sentence": "5 ", "bounding_box": [269, 251, 282, 267]}, {"sentence": "6 ", "bounding_box": [494, 256, 506, 273]}, {"sentence": "13 ", "bounding_box": [262, 281, 290, 300]}, {"sentence": "16 ", "bounding_box": [36, 289, 65, 309]}, {"sentence": "17 ", "bounding_box": [487, 294, 514, 315]}, {"sentence": "24 ", "bounding_box": [335, 305, 365, 326]}, {"sentence": "28 ", "bounding_box": [110, 312, 140, 333]}, {"sentence": "30 ", "bounding_box": [561, 316, 591, 335]}, {"sentence": "82 ", "bounding_box": [260, 442, 290, 461]}, {"sentence": "78 ", "bounding_box": [36, 447, 65, 468]}, {"sentence": "76 ", "bounding_box": [487, 450, 516, 471]}, {"sentence": "69 ", "bounding_box": [335, 462, 365, 483]}, {"sentence": "65 ", "bounding_box": [110, 471, 140, 490]}, {"sentence": "63 ", "bounding_box": [561, 473, 591, 492]}, {"sentence": "Sept ", "bounding_box": [25, 609, 75, 632]}, {"sentence": "April ", "bounding_box": [103, 609, 148, 630]}, {"sentence": "Sept ", "bounding_box": [251, 609, 300, 630]}, {"sentence": "April ", "bounding_box": [327, 609, 374, 630]}, {"sentence": "Sept ", "bounding_box": [476, 609, 525, 630]}, {"sentence": "April ", "bounding_box": [553, 609, 599, 630]}, {"sentence": "2019 2020 ", "bounding_box": [21, 635, 154, 655]}, {"sentence": "2019 2020 ", "bounding_box": [247, 635, 379, 655]}, {"sentence": "2019 2020 ", "bounding_box": [472, 635, 604, 655]}, {"sentence": "Total ", "bounding_box": [57, 666, 111, 685]}, {"sentence": "Rep/ ", "bounding_box": [286, 665, 340, 689]}, {"sentence": "Dem ", "bounding_box": [510, 665, 570, 687]}, {"sentence": "Lean Rep ", "bounding_box": [264, 691, 365, 717]}, {"sentence": "Lean Dem ", "bounding_box": [488, 693, 594, 714]}, {"sentence": "Note: No answer responses not shown ", "bounding_box": [6, 751, 357, 772]}, {"sentence": "Source: Survey of U.S adults conducted April 7-12, 2020 ", "bounding_box": [5, 778, 520, 798]}, {"sentence": "PEW RESEARCH CENTER ", "bounding_box": [6, 816, 234, 834]}]