[{"sentence": "How Student Debt Affects ", "bounding_box": [9, 26, 225, 41]}, {"sentence": "Borrowers ", "bounding_box": [8, 44, 97, 62]}, {"sentence": "% of student borrowers had who say having to pay back ", "bounding_box": [9, 70, 290, 86]}, {"sentence": "student loans had this impacton say having them ", "bounding_box": [7, 84, 217, 102]}, {"sentence": "Harder to Tends pay bills/ ", "bounding_box": [36, 128, 145, 142]}, {"sentence": "48 ", "bounding_box": [258, 136, 274, 148]}, {"sentence": "ma ke Tends pay meet ", "bounding_box": [52, 141, 145, 153]}, {"sentence": "Harder to buy a home ", "bounding_box": [18, 177, 142, 190]}, {"sentence": "25 ", "bounding_box": [210, 180, 226, 192]}, {"sentence": "Impacted ", "bounding_box": [81, 218, 137, 231]}, {"sentence": "24 ", "bounding_box": [209, 224, 224, 236]}, {"sentence": "career choices ", "bounding_box": [55, 231, 138, 243]}, {"sentence": "Delayed marriagel family ", "bounding_box": [38, 260, 142, 273]}, {"sentence": "marriagel family ", "bounding_box": [104, 271, 143, 285]}, {"sentence": "Note: Based on those who took out loans for postse condary ", "bounding_box": [9, 310, 294, 322]}, {"sentence": "educa tion and are not currently enrolled in school, postse n=332, condary ", "bounding_box": [10, 321, 286, 334]}, {"sentence": "PEW RESEARCH CENTER GP/29 ", "bounding_box": [9, 338, 157, 350]}]