[{"sentence": "Rejec tion of Suicide Bombing ", "bounding_box": [47, 7, 230, 25]}, {"sentence": "and Vio lence Against Civilians ", "bounding_box": [46, 29, 231, 45]}, {"sentence": "% Never justified ", "bounding_box": [94, 57, 190, 72]}, {"sentence": "87 ", "bounding_box": [234, 84, 248, 94]}, {"sentence": "Pakistan ", "bounding_box": [25, 85, 70, 96]}, {"sentence": "Turkey ", "bounding_box": [32, 109, 71, 123]}, {"sentence": "74 ", "bounding_box": [209, 109, 224, 120]}, {"sentence": "65 ", "bounding_box": [192, 133, 205, 145]}, {"sentence": "Indonesia ", "bounding_box": [20, 134, 70, 146]}, {"sentence": "52 55 56 ", "bounding_box": [163, 156, 191, 223]}, {"sentence": "Jordan ", "bounding_box": [34, 160, 70, 172]}, {"sentence": "Israel ", "bounding_box": [42, 186, 70, 196]}, {"sentence": "Egypt ", "bounding_box": [38, 209, 70, 222]}, {"sentence": "44 ", "bounding_box": [150, 233, 164, 245]}, {"sentence": "Lebanon ", "bounding_box": [26, 234, 70, 246]}, {"sentence": "Nigeria ", "bounding_box": [31, 258, 71, 273]}, {"sentence": "33 ", "bounding_box": [128, 258, 142, 269]}, {"sentence": "Palest ter ", "bounding_box": [10, 284, 70, 296]}, {"sentence": "Asked of Muslims only ", "bounding_box": [8, 312, 114, 324]}, {"sentence": "\"Some people think that suicide bombing and other ", "bounding_box": [6, 329, 260, 342]}, {"sentence": "forms of violence against civilian targets are ", "bounding_box": [8, 348, 233, 361]}, {"sentence": "justified in order to defend Islam from its enemies ", "bounding_box": [7, 364, 257, 378]}, {"sentence": "Do you personally feel that this kind of violence is ", "bounding_box": [8, 384, 256, 397]}, {"sentence": "often justfied, some times justified, rarely justified, ", "bounding_box": [8, 401, 268, 414]}, {"sentence": "or never justified?\" ", "bounding_box": [7, 419, 105, 434]}]