[{"sentence": "British have little faith in EU ", "bounding_box": [2, 14, 217, 30]}, {"sentence": "Disapprove handling of EU's ", "bounding_box": [22, 44, 120, 57]}, {"sentence": "CONTERTATION ", "bounding_box": [154, 46, 234, 181]}, {"sentence": "70% ", "bounding_box": [269, 52, 294, 65]}, {"sentence": "Disapprove handling refugee of the ", "bounding_box": [41, 57, 120, 72]}, {"sentence": "handling refugee issue ", "bounding_box": [46, 70, 120, 85]}, {"sentence": "EU is inefficient* ", "bounding_box": [26, 97, 116, 109]}, {"sentence": "EU does not ", "bounding_box": [54, 122, 121, 134]}, {"sentence": "understand needs ", "bounding_box": [25, 137, 119, 149]}, {"sentence": "64 ", "bounding_box": [258, 141, 273, 152]}, {"sentence": "of its citizens* ", "bounding_box": [42, 150, 120, 161]}, {"sentence": "Disapprove of EU's ", "bounding_box": [22, 169, 120, 181]}, {"sentence": "handling of European ", "bounding_box": [9, 182, 120, 196]}, {"sentence": "55 ", "bounding_box": [241, 185, 256, 196]}, {"sentence": "economic issues ", "bounding_box": [33, 197, 120, 208]}, {"sentence": "*Data from Spring 2014 Global Attitudes Survey. ", "bounding_box": [1, 221, 225, 234]}, {"sentence": "Source Spring 2016 Global Attitudes Survev. ", "bounding_box": [0, 242, 209, 256]}, {"sentence": "PEW RESEARCH CENTER ", "bounding_box": [1, 262, 118, 273]}]