[{"sentence": "Texting Most Common Use of Cell ", "bounding_box": [0, 13, 258, 30]}, {"sentence": "Phones in Africa ", "bounding_box": [1, 34, 124, 49]}, {"sentence": "Medianadult cell phone owners who useda cell phone in ", "bounding_box": [0, 58, 308, 73]}, {"sentence": "the past 12 months to ", "bounding_box": [0, 74, 128, 89]}, {"sentence": "Send text messages ", "bounding_box": [23, 109, 128, 124]}, {"sentence": "80% ", "bounding_box": [278, 110, 304, 122]}, {"sentence": "Take pictures or video ", "bounding_box": [14, 131, 128, 146]}, {"sentence": "53 ", "bounding_box": [232, 133, 248, 144]}, {"sentence": "Make receive payments ", "bounding_box": [3, 154, 128, 168]}, {"sentence": "30 ", "bounding_box": [192, 154, 206, 166]}, {"sentence": "Get political news ", "bounding_box": [37, 177, 128, 189]}, {"sentence": "14 14 17 19 21 ", "bounding_box": [159, 175, 192, 279]}, {"sentence": "Access social network ", "bounding_box": [14, 200, 128, 210]}, {"sentence": "Get hea 1th info ", "bounding_box": [50, 221, 128, 233]}, {"sentence": "Looky Tapply for a job ", "bounding_box": [25, 244, 128, 257]}, {"sentence": "Get do nsumer info ", "bounding_box": [33, 266, 128, 277]}, {"sentence": "Note: Median percenta ges across seven African countries. ", "bounding_box": [0, 298, 265, 312]}, {"sentence": "Source: Spring 2014 Global Attitud es survey. Q74a-h. ", "bounding_box": [0, 320, 245, 333]}, {"sentence": "PEW RESEARCH CENTER ", "bounding_box": [0, 340, 117, 350]}]